{
    "5ac23c6186f7741247042bad": [
        {
            "findInRaid": true,
            "id": "674f4246cc0bbde12f5bcc1e",
            "index": 0,
            "items": [
                {
                    "_id": "674f242414121869ec032c84",
                    "_tpl": "54491c4f4bdc2db1078b4568",
                    "upd": {
                        "Repairable": {
                            "MaxDurability": 100,
                            "Durability": 100
                        },
                        "FireMode": {
                            "FireMode": "single"
                        }
                    }
                },
                {
                    "_id": "674f242414121869ec032c85",
                    "_tpl": "55d4491a4bdc2d882f8b456e",
                    "slotId": "mod_barrel",
                    "parentId": "674f242414121869ec032c84"
                },
                {
                    "_id": "674f242414121869ec032c86",
                    "_tpl": "55d45d3f4bdc2d972f8b456c",
                    "slotId": "mod_handguard",
                    "parentId": "674f242414121869ec032c84"
                },
                {
                    "_id": "674f242414121869ec032c87",
                    "_tpl": "55d484b44bdc2d1d4e8b456d",
                    "slotId": "mod_magazine",
                    "parentId": "674f242414121869ec032c84"
                },
                {
                    "_id": "674f242414121869ec032c88",
                    "_tpl": "56083cba4bdc2de22e8b456f",
                    "slotId": "mod_stock",
                    "parentId": "674f242414121869ec032c84"
                }
            ],
            "target": "674f242414121869ec032c84",
            "type": "Item",
            "unknown": false,
            "value": 1
        }
    ],
    "5ac2428686f77412450b42bf": [
        {
            "findInRaid": true,
            "id": "674f426d3f4dca929209ef99",
            "index": 0,
            "items": [
                {
                    "_id": "674f2cb8ac7331365c031faa",
                    "_tpl": "5926bb2186f7744b1c6c6e60",
                    "upd": {
                        "Repairable": {
                            "MaxDurability": 100,
                            "Durability": 100
                        },
                        "FireMode": {
                            "FireMode": "single"
                        }
                    }
                },
                {
                    "_id": "674f2cb8ac7331365c031fab",
                    "_tpl": "5926c3b286f774640d189b6b",
                    "slotId": "mod_magazine",
                    "parentId": "674f2cb8ac7331365c031faa"
                },
                {
                    "_id": "674f2cb8ac7331365c031fac",
                    "_tpl": "5926c0df86f77462f647f764",
                    "slotId": "mod_reciever",
                    "parentId": "674f2cb8ac7331365c031faa"
                },
                {
                    "_id": "674f2cb8ac7331365c031fad",
                    "_tpl": "5926c32286f774616e42de99",
                    "slotId": "mod_charge",
                    "parentId": "674f2cb8ac7331365c031faa"
                },
                {
                    "_id": "674f2cb8ac7331365c031fae",
                    "_tpl": "5926c36d86f77467a92a8629",
                    "slotId": "mod_handguard",
                    "parentId": "674f2cb8ac7331365c031fac"
                },
                {
                    "_id": "674f2cb8ac7331365c031faf",
                    "_tpl": "5926d2be86f774134d668e4e",
                    "slotId": "mod_sight_rear",
                    "upd": {
                        "Sight": {
                            "ScopesCurrentCalibPointIndexes": [
                                0
                            ],
                            "ScopesSelectedModes": [
                                0
                            ],
                            "SelectedScope": 0,
                            "ScopeZoomValue": 0
                        }
                    },
                    "parentId": "674f2cb8ac7331365c031fac"
                },
                {
                    "_id": "674f2cb8ac7331365c031fb0",
                    "_tpl": "5926d3c686f77410de68ebc8",
                    "slotId": "mod_stock",
                    "parentId": "674f2cb8ac7331365c031fac"
                },
                {
                    "_id": "674f2cb8ac7331365c031fb1",
                    "_tpl": "5926e16e86f7742f5a0f7ecb",
                    "slotId": "mod_muzzle",
                    "parentId": "674f2cb8ac7331365c031fac"
                }
            ],
            "target": "674f2cb8ac7331365c031faa",
            "type": "Item",
            "unknown": false,
            "value": 1
        }
    ],
    "639872f9decada40426d3447": [
        {
            "findInRaid": true,
            "id": "674f4257f4f927f030145097",
            "index": 0,
            "items": [
                {
                    "_id": "674f2cd2ac7331365c031fbc",
                    "_tpl": "587e02ff24597743df3deaeb",
                    "upd": {
                        "Repairable": {
                            "MaxDurability": 100,
                            "Durability": 100
                        },
                        "FireMode": {
                            "FireMode": "single"
                        }
                    }
                },
                {
                    "_id": "674f2cd2ac7331365c031fbd",
                    "_tpl": "587e0531245977466077a0f7",
                    "slotId": "mod_stock",
                    "parentId": "674f2cd2ac7331365c031fbc"
                },
                {
                    "_id": "674f2cd2ac7331365c031fbe",
                    "_tpl": "634eff66517ccc8a960fc735",
                    "slotId": "mod_barrel",
                    "parentId": "674f2cd2ac7331365c031fbc"
                },
                {
                    "_id": "674f2cd2ac7331365c031fbf",
                    "_tpl": "587df3a12459772c28142567",
                    "slotId": "mod_magazine",
                    "parentId": "674f2cd2ac7331365c031fbc"
                },
                {
                    "_id": "674f2cd2ac7331365c031fc0",
                    "_tpl": "634f06262e5def262d0b30ca",
                    "slotId": "mod_reciever",
                    "parentId": "674f2cd2ac7331365c031fbc"
                },
                {
                    "_id": "674f2cd2ac7331365c031fc1",
                    "_tpl": "634f05a21f9f536910079b56",
                    "slotId": "mod_mount_000",
                    "parentId": "674f2cd2ac7331365c031fbe"
                },
                {
                    "_id": "674f2cd2ac7331365c031fc2",
                    "_tpl": "634f036a517ccc8a960fc746",
                    "slotId": "mod_gas_block",
                    "parentId": "674f2cd2ac7331365c031fc1"
                },
                {
                    "_id": "674f2cd2ac7331365c031fc3",
                    "_tpl": "574db213245977459a2f3f5d",
                    "slotId": "mod_sight_rear",
                    "upd": {
                        "Sight": {
                            "ScopesCurrentCalibPointIndexes": [
                                0
                            ],
                            "ScopesSelectedModes": [
                                0
                            ],
                            "SelectedScope": 0,
                            "ScopeZoomValue": 0
                        }
                    },
                    "parentId": "674f2cd2ac7331365c031fc1"
                },
                {
                    "_id": "674f2cd2ac7331365c031fc4",
                    "_tpl": "634f03d40384a3ba4f06f874",
                    "slotId": "mod_mount_000",
                    "parentId": "674f2cd2ac7331365c031fc2"
                }
            ],
            "target": "674f2cd2ac7331365c031fbc",
            "type": "Item",
            "unknown": false,
            "value": 1
        }
    ],
    "5ae3267986f7742a413592fe": [
        {
            "findInRaid": true,
            "id": "674f427975f61bbb17602a9a",
            "index": 0,
            "items": [
                {
                    "_id": "674f2d57ac7331365c032e6a",
                    "_tpl": "5a7828548dc32e5a9c28b516",
                    "upd": {
                        "Repairable": {
                            "MaxDurability": 100,
                            "Durability": 100
                        },
                        "FireMode": {
                            "FireMode": "single"
                        }
                    }
                },
                {
                    "_id": "674f2d57ac7331365c032e6b",
                    "_tpl": "5a787f7ac5856700177af660",
                    "slotId": "mod_barrel",
                    "parentId": "674f2d57ac7331365c032e6a"
                },
                {
                    "_id": "674f2d57ac7331365c032e6c",
                    "_tpl": "5a788089c5856700142fdd9c",
                    "slotId": "mod_handguard",
                    "parentId": "674f2d57ac7331365c032e6a"
                },
                {
                    "_id": "674f2d57ac7331365c032e6d",
                    "_tpl": "5a7882dcc5856700177af662",
                    "slotId": "mod_magazine",
                    "parentId": "674f2d57ac7331365c032e6a"
                },
                {
                    "_id": "674f2d57ac7331365c032e6e",
                    "_tpl": "5a7880d0c5856700142fdd9d",
                    "slotId": "mod_stock",
                    "parentId": "674f2d57ac7331365c032e6a"
                }
            ],
            "target": "674f2d57ac7331365c032e6a",
            "type": "Item",
            "unknown": false,
            "value": 1
        }
    ],
    "5ae3270f86f77445ba41d4dd": [
        {
            "findInRaid": true,
            "id": "674f428a2f4365f0c7a8732d",
            "index": 0,
            "items": [
                {
                    "_id": "674f2d76ac7331365c032e79",
                    "_tpl": "59d6088586f774275f37482f",
                    "upd": {
                        "Repairable": {
                            "MaxDurability": 100,
                            "Durability": 100
                        },
                        "FireMode": {
                            "FireMode": "single"
                        }
                    }
                },
                {
                    "_id": "674f2d76ac7331365c032e7a",
                    "_tpl": "59d64ec286f774171d1e0a42",
                    "slotId": "mod_gas_block",
                    "parentId": "674f2d76ac7331365c032e79"
                },
                {
                    "_id": "674f2d76ac7331365c032e7b",
                    "_tpl": "59d64fc686f774171b243fe2",
                    "slotId": "mod_muzzle",
                    "parentId": "674f2d76ac7331365c032e79"
                },
                {
                    "_id": "674f2d76ac7331365c032e7c",
                    "_tpl": "59e62cc886f77440d40b52a1",
                    "slotId": "mod_pistol_grip",
                    "parentId": "674f2d76ac7331365c032e79"
                },
                {
                    "_id": "674f2d76ac7331365c032e7d",
                    "_tpl": "59d6507c86f7741b846413a2",
                    "slotId": "mod_reciever",
                    "parentId": "674f2d76ac7331365c032e79"
                },
                {
                    "_id": "674f2d76ac7331365c032e7e",
                    "_tpl": "59d650cf86f7741b846413a4",
                    "slotId": "mod_sight_rear",
                    "upd": {
                        "Sight": {
                            "ScopesCurrentCalibPointIndexes": [
                                0
                            ],
                            "ScopesSelectedModes": [
                                0
                            ],
                            "SelectedScope": 0,
                            "ScopeZoomValue": 0
                        }
                    },
                    "parentId": "674f2d76ac7331365c032e79"
                },
                {
                    "_id": "674f2d76ac7331365c032e7f",
                    "_tpl": "59d6514b86f774171a068a08",
                    "slotId": "mod_stock",
                    "parentId": "674f2d76ac7331365c032e79"
                },
                {
                    "_id": "674f2d76ac7331365c032e80",
                    "_tpl": "59d625f086f774661516605d",
                    "slotId": "mod_magazine",
                    "parentId": "674f2d76ac7331365c032e79"
                },
                {
                    "_id": "674f2d76ac7331365c032e81",
                    "_tpl": "59d64f2f86f77417193ef8b3",
                    "slotId": "mod_handguard",
                    "parentId": "674f2d76ac7331365c032e7a"
                }
            ],
            "target": "674f2d76ac7331365c032e79",
            "type": "Item",
            "unknown": false,
            "value": 1
        }
    ],
    "5ac244eb86f7741356335af1": [
        {
            "findInRaid": true,
            "id": "674f535c40c5421a4fffe754",
            "index": 0,
            "items": [
                {
                    "_id": "674f5c6a6341e68384033f7e",
                    "_tpl": "5447a9cd4bdc2dbd208b4567",
                    "upd": {
                        "Repairable": {
                            "MaxDurability": 100,
                            "Durability": 100
                        },
                        "FireMode": {
                            "FireMode": "single"
                        }
                    }
                },
                {
                    "_id": "674f5c6a6341e68384033f7f",
                    "_tpl": "55d4b9964bdc2d1d4e8b456e",
                    "slotId": "mod_pistol_grip",
                    "parentId": "674f5c6a6341e68384033f7e"
                },
                {
                    "_id": "674f5c6a6341e68384033f80",
                    "_tpl": "55d4887d4bdc2d962f8b4570",
                    "slotId": "mod_magazine",
                    "parentId": "674f5c6a6341e68384033f7e"
                },
                {
                    "_id": "674f5c6a6341e68384033f81",
                    "_tpl": "55d355e64bdc2d962f8b4569",
                    "slotId": "mod_reciever",
                    "parentId": "674f5c6a6341e68384033f7e"
                },
                {
                    "_id": "674f5c6a6341e68384033f82",
                    "_tpl": "5649be884bdc2d79388b4577",
                    "slotId": "mod_stock",
                    "parentId": "674f5c6a6341e68384033f7e"
                },
                {
                    "_id": "674f5c6a6341e68384033f83",
                    "_tpl": "55d44fd14bdc2d962f8b456e",
                    "slotId": "mod_charge",
                    "parentId": "674f5c6a6341e68384033f7e"
                },
                {
                    "_id": "674f5c6a6341e68384033f84",
                    "_tpl": "55d3632e4bdc2d972f8b4569",
                    "slotId": "mod_barrel",
                    "parentId": "674f5c6a6341e68384033f81"
                },
                {
                    "_id": "674f5c6a6341e68384033f85",
                    "_tpl": "5ae30db85acfc408fb139a05",
                    "slotId": "mod_handguard",
                    "parentId": "674f5c6a6341e68384033f81"
                },
                {
                    "_id": "674f5c6a6341e68384033f86",
                    "_tpl": "5ae30bad5acfc400185c2dc4",
                    "slotId": "mod_sight_rear",
                    "upd": {
                        "Sight": {
                            "ScopesCurrentCalibPointIndexes": [
                                0
                            ],
                            "ScopesSelectedModes": [
                                0
                            ],
                            "SelectedScope": 0,
                            "ScopeZoomValue": 0
                        }
                    },
                    "parentId": "674f5c6a6341e68384033f81"
                },
                {
                    "_id": "674f5c6a6341e68384033f87",
                    "_tpl": "55d4ae6c4bdc2d8b2f8b456e",
                    "slotId": "mod_stock_000",
                    "parentId": "674f5c6a6341e68384033f82"
                },
                {
                    "_id": "674f5c6a6341e68384033f88",
                    "_tpl": "544a38634bdc2d58388b4568",
                    "slotId": "mod_muzzle",
                    "parentId": "674f5c6a6341e68384033f84"
                },
                {
                    "_id": "674f5c6a6341e68384033f89",
                    "_tpl": "5ae30e795acfc408fb139a0b",
                    "slotId": "mod_gas_block",
                    "parentId": "674f5c6a6341e68384033f84"
                },
                {
                    "_id": "674f5c6a6341e68384033f8a",
                    "_tpl": "637f57a68d137b27f70c4968",
                    "slotId": "mod_handguard",
                    "parentId": "674f5c6a6341e68384033f85"
                }
            ],
            "target": "674f5c6a6341e68384033f7e",
            "type": "Item",
            "unknown": false,
            "value": 1
        }
    ],
    "5ae3277186f7745973054106": [
        {
            "findInRaid": true,
            "id": "674f5365b6de80b3784ef1d8",
            "index": 0,
            "items": [
                {
                    "_id": "674f4f1b67b1cd4418031f47",
                    "_tpl": "5ab8e9fcd8ce870019439434",
                    "upd": {
                        "Repairable": {
                            "MaxDurability": 100,
                            "Durability": 100
                        },
                        "Foldable": {
                            "Folded": false
                        },
                        "FireMode": {
                            "FireMode": "single"
                        }
                    }
                },
                {
                    "_id": "674f4f1b67b1cd4418031f48",
                    "_tpl": "59c6633186f7740cf0493bb9",
                    "slotId": "mod_gas_block",
                    "parentId": "674f4f1b67b1cd4418031f47"
                },
                {
                    "_id": "674f4f1b67b1cd4418031f49",
                    "_tpl": "5649aa744bdc2ded0b8b457e",
                    "slotId": "mod_muzzle",
                    "parentId": "674f4f1b67b1cd4418031f47"
                },
                {
                    "_id": "674f4f1b67b1cd4418031f4a",
                    "_tpl": "57e3dba62459770f0c32322b",
                    "slotId": "mod_pistol_grip",
                    "parentId": "674f4f1b67b1cd4418031f47"
                },
                {
                    "_id": "674f4f1b67b1cd4418031f4b",
                    "_tpl": "5649af094bdc2df8348b4586",
                    "slotId": "mod_reciever",
                    "parentId": "674f4f1b67b1cd4418031f47"
                },
                {
                    "_id": "674f4f1b67b1cd4418031f4c",
                    "_tpl": "5649b0544bdc2d1b2b8b458a",
                    "slotId": "mod_sight_rear",
                    "upd": {
                        "Sight": {
                            "ScopesCurrentCalibPointIndexes": [
                                0
                            ],
                            "ScopesSelectedModes": [
                                0
                            ],
                            "SelectedScope": 0,
                            "ScopeZoomValue": 0
                        }
                    },
                    "parentId": "674f4f1b67b1cd4418031f47"
                },
                {
                    "_id": "674f4f1b67b1cd4418031f4d",
                    "_tpl": "5ab626e4d8ce87272e4c6e43",
                    "slotId": "mod_stock",
                    "parentId": "674f4f1b67b1cd4418031f47"
                },
                {
                    "_id": "674f4f1b67b1cd4418031f4e",
                    "_tpl": "564ca99c4bdc2d16268b4589",
                    "slotId": "mod_magazine",
                    "parentId": "674f4f1b67b1cd4418031f47"
                },
                {
                    "_id": "674f4f1b67b1cd4418031f4f",
                    "_tpl": "5648b0744bdc2d363b8b4578",
                    "slotId": "mod_handguard",
                    "parentId": "674f4f1b67b1cd4418031f48"
                }
            ],
            "target": "674f4f1b67b1cd4418031f47",
            "type": "Item",
            "unknown": false,
            "value": 1
        }
    ],
    "639872fa9b4fb827b200d8e5": [
        {
            "findInRaid": true,
            "id": "674f5369ffbc6d86d0b4d8ee",
            "index": 0,
            "items": [
                {
                    "_id": "674f4f3567b1cd4418031f58",
                    "_tpl": "56d59856d2720bd8418b456a",
                    "upd": {
                        "Repairable": {
                            "MaxDurability": 100,
                            "Durability": 100
                        },
                        "FireMode": {
                            "FireMode": "single"
                        }
                    }
                },
                {
                    "_id": "674f4f3567b1cd4418031f59",
                    "_tpl": "56d5a1f7d2720bb3418b456a",
                    "slotId": "mod_barrel",
                    "parentId": "674f4f3567b1cd4418031f58"
                },
                {
                    "_id": "674f4f3567b1cd4418031f5a",
                    "_tpl": "56d5a2bbd2720bb8418b456a",
                    "slotId": "mod_pistol_grip",
                    "parentId": "674f4f3567b1cd4418031f58"
                },
                {
                    "_id": "674f4f3567b1cd4418031f5b",
                    "_tpl": "56d5a407d2720bb3418b456b",
                    "slotId": "mod_reciever",
                    "parentId": "674f4f3567b1cd4418031f58"
                },
                {
                    "_id": "674f4f3567b1cd4418031f5c",
                    "_tpl": "56d59948d2720bb7418b4582",
                    "slotId": "mod_magazine",
                    "parentId": "674f4f3567b1cd4418031f58"
                },
                {
                    "_id": "674f4f3567b1cd4418031f5d",
                    "_tpl": "56d5a77ed2720b90418b4568",
                    "slotId": "mod_sight_rear",
                    "upd": {
                        "Sight": {
                            "ScopesCurrentCalibPointIndexes": [
                                0
                            ],
                            "ScopesSelectedModes": [
                                0
                            ],
                            "SelectedScope": 0,
                            "ScopeZoomValue": 0
                        }
                    },
                    "parentId": "674f4f3567b1cd4418031f5b"
                },
                {
                    "_id": "674f4f3567b1cd4418031f5e",
                    "_tpl": "56d5a661d2720bd8418b456b",
                    "slotId": "mod_sight_front",
                    "upd": {
                        "Sight": {
                            "ScopesCurrentCalibPointIndexes": [
                                0
                            ],
                            "ScopesSelectedModes": [
                                0
                            ],
                            "SelectedScope": 0,
                            "ScopeZoomValue": 0
                        }
                    },
                    "parentId": "674f4f3567b1cd4418031f5b"
                }
            ],
            "target": "674f4f3567b1cd4418031f58",
            "type": "Item",
            "unknown": false,
            "value": 1
        }
    ],
    "5ae327c886f7745c7b3f2f3f": [
        {
            "findInRaid": true,
            "id": "674f536ef07d9eadf07be803",
            "index": 0,
            "items": [
                {
                    "_id": "674f4f5167b1cd4418031f69",
                    "_tpl": "5ac66d9b5acfc4001633997a",
                    "upd": {
                        "Repairable": {
                            "MaxDurability": 100,
                            "Durability": 100
                        },
                        "Foldable": {
                            "Folded": false
                        },
                        "FireMode": {
                            "FireMode": "single"
                        }
                    }
                },
                {
                    "_id": "674f4f5167b1cd4418031f6a",
                    "_tpl": "59c6633186f7740cf0493bb9",
                    "slotId": "mod_gas_block",
                    "parentId": "674f4f5167b1cd4418031f69"
                },
                {
                    "_id": "674f4f5167b1cd4418031f6b",
                    "_tpl": "5ac72e945acfc43f3b691116",
                    "slotId": "mod_muzzle",
                    "parentId": "674f4f5167b1cd4418031f69"
                },
                {
                    "_id": "674f4f5167b1cd4418031f6c",
                    "_tpl": "5649ade84bdc2d1b2b8b4587",
                    "slotId": "mod_pistol_grip",
                    "parentId": "674f4f5167b1cd4418031f69"
                },
                {
                    "_id": "674f4f5167b1cd4418031f6d",
                    "_tpl": "5ac50da15acfc4001718d287",
                    "slotId": "mod_reciever",
                    "parentId": "674f4f5167b1cd4418031f69"
                },
                {
                    "_id": "674f4f5167b1cd4418031f6e",
                    "_tpl": "5ac733a45acfc400192630e2",
                    "slotId": "mod_sight_rear",
                    "upd": {
                        "Sight": {
                            "ScopesCurrentCalibPointIndexes": [
                                0
                            ],
                            "ScopesSelectedModes": [
                                0
                            ],
                            "SelectedScope": 0,
                            "ScopeZoomValue": 0
                        }
                    },
                    "parentId": "674f4f5167b1cd4418031f69"
                },
                {
                    "_id": "674f4f5167b1cd4418031f6f",
                    "_tpl": "5ac50c185acfc400163398d4",
                    "slotId": "mod_stock",
                    "parentId": "674f4f5167b1cd4418031f69"
                },
                {
                    "_id": "674f4f5167b1cd4418031f70",
                    "_tpl": "55d480c04bdc2d1d4e8b456a",
                    "slotId": "mod_magazine",
                    "parentId": "674f4f5167b1cd4418031f69"
                },
                {
                    "_id": "674f4f5167b1cd4418031f71",
                    "_tpl": "5648b1504bdc2d9d488b4584",
                    "slotId": "mod_handguard",
                    "parentId": "674f4f5167b1cd4418031f6a"
                }
            ],
            "target": "674f4f5167b1cd4418031f69",
            "type": "Item",
            "unknown": false,
            "value": 1
        }
    ],
    "639872fc93ae507d5858c3a6": [
        {
            "findInRaid": true,
            "id": "674f53719ee2d6144c998540",
            "index": 0,
            "items": [
                {
                    "_id": "674f552f67b1cd441803feee",
                    "_tpl": "5fc3f2d5900b1d5091531e57",
                    "upd": {
                        "Repairable": {
                            "MaxDurability": 100,
                            "Durability": 100
                        },
                        "Foldable": {
                            "Folded": false
                        },
                        "FireMode": {
                            "FireMode": "single"
                        }
                    }
                },
                {
                    "_id": "674f552f67b1cd441803feef",
                    "_tpl": "5a718b548dc32e000d46d262",
                    "slotId": "mod_magazine",
                    "parentId": "674f552f67b1cd441803feee"
                },
                {
                    "_id": "674f552f67b1cd441803fef0",
                    "_tpl": "5fb6567747ce63734e3fa1dc",
                    "slotId": "mod_sight_front",
                    "upd": {
                        "Sight": {
                            "ScopesCurrentCalibPointIndexes": [
                                0
                            ],
                            "ScopesSelectedModes": [
                                0
                            ],
                            "SelectedScope": 0,
                            "ScopeZoomValue": 0
                        }
                    },
                    "parentId": "674f552f67b1cd441803feee"
                },
                {
                    "_id": "674f552f67b1cd441803fef1",
                    "_tpl": "5fb6564947ce63734e3fa1da",
                    "slotId": "mod_sight_rear",
                    "upd": {
                        "Sight": {
                            "ScopesCurrentCalibPointIndexes": [
                                0
                            ],
                            "ScopesSelectedModes": [
                                0
                            ],
                            "SelectedScope": 0,
                            "ScopeZoomValue": 0
                        }
                    },
                    "parentId": "674f552f67b1cd441803feee"
                },
                {
                    "_id": "674f552f67b1cd441803fef2",
                    "_tpl": "5fb6558ad6f0b2136f2d7eb7",
                    "slotId": "mod_stock",
                    "parentId": "674f552f67b1cd441803feee"
                },
                {
                    "_id": "674f552f67b1cd441803fef3",
                    "_tpl": "5fbbc366ca32ed67276c1557",
                    "slotId": "mod_barrel",
                    "parentId": "674f552f67b1cd441803feee"
                },
                {
                    "_id": "674f552f67b1cd441803fef4",
                    "_tpl": "5fbb976df9986c4cff3fe5f2",
                    "slotId": "mod_mount",
                    "parentId": "674f552f67b1cd441803feee"
                },
                {
                    "_id": "674f552f67b1cd441803fef5",
                    "_tpl": "5fce0f9b55375d18a253eff2",
                    "slotId": "mod_mount_001",
                    "parentId": "674f552f67b1cd441803feee"
                },
                {
                    "_id": "674f552f67b1cd441803fef6",
                    "_tpl": "5fce0f9b55375d18a253eff2",
                    "slotId": "mod_mount_002",
                    "parentId": "674f552f67b1cd441803feee"
                },
                {
                    "_id": "674f552f67b1cd441803fef7",
                    "_tpl": "5fbbc34106bde7524f03cbe9",
                    "slotId": "mod_muzzle",
                    "parentId": "674f552f67b1cd441803fef3"
                }
            ],
            "target": "674f552f67b1cd441803feee",
            "type": "Item",
            "unknown": false,
            "value": 1
        }
    ],
    "5b47799d86f7746c5d6a5fd8": [
        {
            "findInRaid": true,
            "id": "674f5378aaa384d5db83a96f",
            "index": 0,
            "items": [
                {
                    "_id": "674f554867b1cd4418040daf",
                    "_tpl": "58948c8e86f77409493f7266",
                    "upd": {
                        "Repairable": {
                            "MaxDurability": 100,
                            "Durability": 100
                        },
                        "FireMode": {
                            "FireMode": "single"
                        }
                    }
                },
                {
                    "_id": "674f554867b1cd4418040db0",
                    "_tpl": "5894a51286f77426d13baf02",
                    "slotId": "mod_pistol_grip",
                    "parentId": "674f554867b1cd4418040daf"
                },
                {
                    "_id": "674f554867b1cd4418040db1",
                    "_tpl": "5894a05586f774094708ef75",
                    "slotId": "mod_magazine",
                    "parentId": "674f554867b1cd4418040daf"
                },
                {
                    "_id": "674f554867b1cd4418040db2",
                    "_tpl": "5894a5b586f77426d2590767",
                    "slotId": "mod_reciever",
                    "parentId": "674f554867b1cd4418040daf"
                },
                {
                    "_id": "674f554867b1cd4418040db3",
                    "_tpl": "5894a13e86f7742405482982",
                    "slotId": "mod_stock",
                    "parentId": "674f554867b1cd4418040daf"
                },
                {
                    "_id": "674f554867b1cd4418040db4",
                    "_tpl": "58949edd86f77409483e16a9",
                    "slotId": "mod_charge",
                    "parentId": "674f554867b1cd4418040daf"
                },
                {
                    "_id": "674f554867b1cd4418040db5",
                    "_tpl": "5894a2c386f77427140b8342",
                    "slotId": "mod_barrel",
                    "parentId": "674f554867b1cd4418040db2"
                },
                {
                    "_id": "674f554867b1cd4418040db6",
                    "_tpl": "5894a42086f77426d2590762",
                    "slotId": "mod_handguard",
                    "parentId": "674f554867b1cd4418040db2"
                },
                {
                    "_id": "674f554867b1cd4418040db7",
                    "_tpl": "5894a81786f77427140b8347",
                    "slotId": "mod_sight_rear",
                    "upd": {
                        "Sight": {
                            "ScopesCurrentCalibPointIndexes": [
                                0
                            ],
                            "ScopesSelectedModes": [
                                0
                            ],
                            "SelectedScope": 0,
                            "ScopeZoomValue": 0
                        }
                    },
                    "parentId": "674f554867b1cd4418040db2"
                },
                {
                    "_id": "674f554867b1cd4418040db8",
                    "_tpl": "58949dea86f77409483e16a8",
                    "slotId": "mod_muzzle",
                    "parentId": "674f554867b1cd4418040db5"
                },
                {
                    "_id": "674f554867b1cd4418040db9",
                    "_tpl": "5894a73486f77426d259076c",
                    "slotId": "mod_sight_front",
                    "upd": {
                        "Sight": {
                            "ScopesCurrentCalibPointIndexes": [
                                0
                            ],
                            "ScopesSelectedModes": [
                                0
                            ],
                            "SelectedScope": 0,
                            "ScopeZoomValue": 0
                        }
                    },
                    "parentId": "674f554867b1cd4418040db6"
                },
                {
                    "_id": "674f554867b1cd4418040dba",
                    "_tpl": "58a56f8d86f774651579314c",
                    "slotId": "mod_mount_000",
                    "parentId": "674f554867b1cd4418040db6"
                },
                {
                    "_id": "674f554867b1cd4418040dbb",
                    "_tpl": "58a5c12e86f7745d585a2b9e",
                    "slotId": "mod_mount_001",
                    "parentId": "674f554867b1cd4418040db6"
                },
                {
                    "_id": "674f554867b1cd4418040dbc",
                    "_tpl": "58a56f8d86f774651579314c",
                    "slotId": "mod_mount_002",
                    "parentId": "674f554867b1cd4418040db6"
                }
            ],
            "target": "674f554867b1cd4418040daf",
            "type": "Item",
            "unknown": false,
            "value": 1
        }
    ],
    "5ac244c486f77413e12cf945": [
        {
            "findInRaid": true,
            "id": "674f537bc4e4ba7150c3d662",
            "index": 0,
            "items": [
                {
                    "_id": "674f55b067b1cd4418041cf3",
                    "_tpl": "5a367e5dc4a282000e49738f",
                    "upd": {
                        "Repairable": {
                            "MaxDurability": 100,
                            "Durability": 100
                        },
                        "FireMode": {
                            "FireMode": "single"
                        }
                    }
                },
                {
                    "_id": "674f55b067b1cd4418041cf4",
                    "_tpl": "5a339805c4a2826c6e06d73d",
                    "slotId": "mod_pistol_grip",
                    "parentId": "674f55b067b1cd4418041cf3"
                },
                {
                    "_id": "674f55b067b1cd4418041cf5",
                    "_tpl": "5a3501acc4a282000d72293a",
                    "slotId": "mod_magazine",
                    "parentId": "674f55b067b1cd4418041cf3"
                },
                {
                    "_id": "674f55b067b1cd4418041cf6",
                    "_tpl": "5a33ca0fc4a282000d72292f",
                    "slotId": "mod_stock",
                    "parentId": "674f55b067b1cd4418041cf3"
                },
                {
                    "_id": "674f55b067b1cd4418041cf7",
                    "_tpl": "5a329052c4a28200741e22d3",
                    "slotId": "mod_handguard",
                    "parentId": "674f55b067b1cd4418041cf3"
                },
                {
                    "_id": "674f55b067b1cd4418041cf8",
                    "_tpl": "5a34fae7c4a2826c6e06d760",
                    "slotId": "mod_barrel",
                    "parentId": "674f55b067b1cd4418041cf3"
                },
                {
                    "_id": "674f55b067b1cd4418041cf9",
                    "_tpl": "5a33cae9c4a28232980eb086",
                    "slotId": "mod_stock",
                    "parentId": "674f55b067b1cd4418041cf6"
                },
                {
                    "_id": "674f55b067b1cd4418041cfa",
                    "_tpl": "5a34fd2bc4a282329a73b4c5",
                    "slotId": "mod_muzzle",
                    "parentId": "674f55b067b1cd4418041cf8"
                },
                {
                    "_id": "674f55b067b1cd4418041cfb",
                    "_tpl": "5a34fbadc4a28200741e230a",
                    "slotId": "mod_gas_block",
                    "parentId": "674f55b067b1cd4418041cf8"
                }
            ],
            "target": "674f55b067b1cd4418041cf3",
            "type": "Item",
            "unknown": false,
            "value": 1
        }
    ],
    "639872fe8871e1272b10ccf6": [
        {
            "findInRaid": true,
            "id": "674f5384eae96a94550eb378",
            "index": 0,
            "items": [
                {
                    "_id": "674f568467b1cd441804598e",
                    "_tpl": "5bb2475ed4351e00853264e3",
                    "upd": {
                        "Repairable": {
                            "MaxDurability": 100,
                            "Durability": 100
                        },
                        "FireMode": {
                            "FireMode": "single"
                        }
                    }
                },
                {
                    "_id": "674f568467b1cd441804598f",
                    "_tpl": "5bb20e0ed4351e3bac1212dc",
                    "slotId": "mod_pistol_grip",
                    "parentId": "674f568467b1cd441804598e"
                },
                {
                    "_id": "674f568467b1cd4418045990",
                    "_tpl": "5c05413a0db834001c390617",
                    "slotId": "mod_magazine",
                    "parentId": "674f568467b1cd441804598e"
                },
                {
                    "_id": "674f568467b1cd4418045991",
                    "_tpl": "5bb20d53d4351e4502010a69",
                    "slotId": "mod_reciever",
                    "parentId": "674f568467b1cd441804598e"
                },
                {
                    "_id": "674f568467b1cd4418045992",
                    "_tpl": "5bb20e58d4351e00320205d7",
                    "slotId": "mod_stock",
                    "parentId": "674f568467b1cd441804598e"
                },
                {
                    "_id": "674f568467b1cd4418045993",
                    "_tpl": "5bb20dbcd4351e44f824c04e",
                    "slotId": "mod_charge",
                    "parentId": "674f568467b1cd441804598e"
                },
                {
                    "_id": "674f568467b1cd4418045994",
                    "_tpl": "5bb20d9cd4351e00334c9d8a",
                    "slotId": "mod_barrel",
                    "parentId": "674f568467b1cd4418045991"
                },
                {
                    "_id": "674f568467b1cd4418045995",
                    "_tpl": "5bb20de5d4351e0035629e59",
                    "slotId": "mod_handguard",
                    "parentId": "674f568467b1cd4418045991"
                },
                {
                    "_id": "674f568467b1cd4418045996",
                    "_tpl": "5bb20e49d4351e3bac1212de",
                    "slotId": "mod_sight_rear",
                    "upd": {
                        "Sight": {
                            "ScopesCurrentCalibPointIndexes": [
                                0
                            ],
                            "ScopesSelectedModes": [
                                0
                            ],
                            "SelectedScope": 0,
                            "ScopeZoomValue": 0
                        }
                    },
                    "parentId": "674f568467b1cd4418045991"
                },
                {
                    "_id": "674f568467b1cd4418045997",
                    "_tpl": "5bb20e70d4351e0035629f8f",
                    "slotId": "mod_stock_000",
                    "parentId": "674f568467b1cd4418045992"
                },
                {
                    "_id": "674f568467b1cd4418045998",
                    "_tpl": "544a38634bdc2d58388b4568",
                    "slotId": "mod_muzzle",
                    "parentId": "674f568467b1cd4418045994"
                },
                {
                    "_id": "674f568467b1cd4418045999",
                    "_tpl": "5bb20dcad4351e3bac1212da",
                    "slotId": "mod_gas_block",
                    "parentId": "674f568467b1cd4418045994"
                }
            ],
            "target": "674f568467b1cd441804598e",
            "type": "Item",
            "unknown": false,
            "value": 1
        }
    ],
    "5ae3280386f7742a41359364": [
        {
            "findInRaid": true,
            "id": "674f538901dfe29c49f2dfa7",
            "index": 0,
            "items": [
                {
                    "_id": "674f569967b1cd44180459a3",
                    "_tpl": "57c44b372459772d2b39b8ce",
                    "upd": {
                        "Repairable": {
                            "MaxDurability": 100,
                            "Durability": 100
                        },
                        "Foldable": {
                            "Folded": false
                        },
                        "FireMode": {
                            "FireMode": "single"
                        }
                    }
                },
                {
                    "_id": "674f569967b1cd44180459a4",
                    "_tpl": "57c44dd02459772d2e0ae249",
                    "slotId": "mod_muzzle",
                    "parentId": "674f569967b1cd44180459a3"
                },
                {
                    "_id": "674f569967b1cd44180459a5",
                    "_tpl": "57c44f4f2459772d2c627113",
                    "slotId": "mod_reciever",
                    "parentId": "674f569967b1cd44180459a3"
                },
                {
                    "_id": "674f569967b1cd44180459a6",
                    "_tpl": "57838f9f2459774a150289a0",
                    "slotId": "mod_magazine",
                    "parentId": "674f569967b1cd44180459a3"
                },
                {
                    "_id": "674f569967b1cd44180459a7",
                    "_tpl": "57c44fa82459772d2d75e415",
                    "slotId": "mod_pistol_grip",
                    "parentId": "674f569967b1cd44180459a3"
                },
                {
                    "_id": "674f569967b1cd44180459a8",
                    "_tpl": "57c450252459772d28133253",
                    "slotId": "mod_stock",
                    "parentId": "674f569967b1cd44180459a3"
                },
                {
                    "_id": "674f569967b1cd44180459a9",
                    "_tpl": "651178336cad06c37c049eb4",
                    "slotId": "mod_handguard",
                    "parentId": "674f569967b1cd44180459a3"
                },
                {
                    "_id": "674f569967b1cd44180459aa",
                    "_tpl": "57c44e7b2459772d28133248",
                    "slotId": "mod_sight_rear",
                    "upd": {
                        "Sight": {
                            "ScopesCurrentCalibPointIndexes": [
                                0
                            ],
                            "ScopesSelectedModes": [
                                0
                            ],
                            "SelectedScope": 0,
                            "ScopeZoomValue": 0
                        }
                    },
                    "parentId": "674f569967b1cd44180459a4"
                }
            ],
            "target": "674f569967b1cd44180459a3",
            "type": "Item",
            "unknown": false,
            "value": 1
        }
    ],
    "5ac242ab86f77412464f68b4": [
        {
            "findInRaid": true,
            "id": "674f538b392a4f5c8bf79d93",
            "index": 0,
            "items": [
                {
                    "_id": "674f57b867b1cd441804a290",
                    "_tpl": "588892092459774ac91d4b11",
                    "upd": {
                        "Repairable": {
                            "MaxDurability": 100,
                            "Durability": 100
                        },
                        "Foldable": {
                            "Folded": false
                        },
                        "FireMode": {
                            "FireMode": "single"
                        }
                    }
                },
                {
                    "_id": "674f57b867b1cd441804a291",
                    "_tpl": "5888988e24597752fe43a6fa",
                    "slotId": "mod_magazine",
                    "parentId": "674f57b867b1cd441804a290"
                },
                {
                    "_id": "674f57b867b1cd441804a292",
                    "_tpl": "5888956924597752983e182d",
                    "slotId": "mod_barrel",
                    "parentId": "674f57b867b1cd441804a290"
                },
                {
                    "_id": "674f57b867b1cd441804a293",
                    "_tpl": "57c55f172459772d27602381",
                    "slotId": "mod_pistol_grip",
                    "parentId": "674f57b867b1cd441804a290"
                },
                {
                    "_id": "674f57b867b1cd441804a294",
                    "_tpl": "58889d0c2459775bc215d981",
                    "slotId": "mod_stock",
                    "parentId": "674f57b867b1cd441804a290"
                },
                {
                    "_id": "674f57b867b1cd441804a295",
                    "_tpl": "5888996c24597754281f9419",
                    "slotId": "mod_muzzle",
                    "parentId": "674f57b867b1cd441804a292"
                },
                {
                    "_id": "674f57b867b1cd441804a296",
                    "_tpl": "5888976c24597754281f93f5",
                    "slotId": "mod_handguard",
                    "parentId": "674f57b867b1cd441804a292"
                }
            ],
            "target": "674f57b867b1cd441804a290",
            "type": "Item",
            "unknown": false,
            "value": 1
        }
    ],
    "5b47749f86f7746c5d6a5fd4": [
        {
            "findInRaid": true,
            "id": "674f538fddf997c7f080b89a",
            "index": 0,
            "items": [
                {
                    "_id": "674f57d167b1cd441804a2a1",
                    "_tpl": "5ac66d015acfc400180ae6e4",
                    "upd": {
                        "Repairable": {
                            "MaxDurability": 100,
                            "Durability": 100
                        },
                        "Foldable": {
                            "Folded": false
                        },
                        "FireMode": {
                            "FireMode": "single"
                        }
                    }
                },
                {
                    "_id": "674f57d167b1cd441804a2a2",
                    "_tpl": "59c6633186f7740cf0493bb9",
                    "slotId": "mod_gas_block",
                    "parentId": "674f57d167b1cd441804a2a1"
                },
                {
                    "_id": "674f57d167b1cd441804a2a3",
                    "_tpl": "5ac72e725acfc400180ae701",
                    "slotId": "mod_muzzle",
                    "parentId": "674f57d167b1cd441804a2a1"
                },
                {
                    "_id": "674f57d167b1cd441804a2a4",
                    "_tpl": "5649ade84bdc2d1b2b8b4587",
                    "slotId": "mod_pistol_grip",
                    "parentId": "674f57d167b1cd441804a2a1"
                },
                {
                    "_id": "674f57d167b1cd441804a2a5",
                    "_tpl": "5ac50da15acfc4001718d287",
                    "slotId": "mod_reciever",
                    "parentId": "674f57d167b1cd441804a2a1"
                },
                {
                    "_id": "674f57d167b1cd441804a2a6",
                    "_tpl": "5ac733a45acfc400192630e2",
                    "slotId": "mod_sight_rear",
                    "upd": {
                        "Sight": {
                            "ScopesCurrentCalibPointIndexes": [
                                0
                            ],
                            "ScopesSelectedModes": [
                                0
                            ],
                            "SelectedScope": 0,
                            "ScopeZoomValue": 0
                        }
                    },
                    "parentId": "674f57d167b1cd441804a2a1"
                },
                {
                    "_id": "674f57d167b1cd441804a2a7",
                    "_tpl": "5ac50c185acfc400163398d4",
                    "slotId": "mod_stock",
                    "parentId": "674f57d167b1cd441804a2a1"
                },
                {
                    "_id": "674f57d167b1cd441804a2a8",
                    "_tpl": "5ac66c5d5acfc4001718d314",
                    "slotId": "mod_magazine",
                    "parentId": "674f57d167b1cd441804a2a1"
                },
                {
                    "_id": "674f57d167b1cd441804a2a9",
                    "_tpl": "5648b1504bdc2d9d488b4584",
                    "slotId": "mod_handguard",
                    "parentId": "674f57d167b1cd441804a2a2"
                }
            ],
            "target": "674f57d167b1cd441804a2a1",
            "type": "Item",
            "unknown": false,
            "value": 1
        }
    ],
    "5b477b6f86f7747290681823": [
        {
            "findInRaid": true,
            "id": "674f53943a1b494d1d6926f4",
            "index": 0,
            "items": [
                {
                    "_id": "674f57ec67b1cd441804b16c",
                    "_tpl": "5a0ec13bfcdbcb00165aa685",
                    "upd": {
                        "Repairable": {
                            "MaxDurability": 100,
                            "Durability": 100
                        },
                        "FireMode": {
                            "FireMode": "single"
                        }
                    }
                },
                {
                    "_id": "674f57ec67b1cd441804b16d",
                    "_tpl": "59d64ec286f774171d1e0a42",
                    "slotId": "mod_gas_block",
                    "parentId": "674f57ec67b1cd441804b16c"
                },
                {
                    "_id": "674f57ec67b1cd441804b16e",
                    "_tpl": "59d64fc686f774171b243fe2",
                    "slotId": "mod_muzzle",
                    "parentId": "674f57ec67b1cd441804b16c"
                },
                {
                    "_id": "674f57ec67b1cd441804b16f",
                    "_tpl": "59e62cc886f77440d40b52a1",
                    "slotId": "mod_pistol_grip",
                    "parentId": "674f57ec67b1cd441804b16c"
                },
                {
                    "_id": "674f57ec67b1cd441804b170",
                    "_tpl": "59d6507c86f7741b846413a2",
                    "slotId": "mod_reciever",
                    "parentId": "674f57ec67b1cd441804b16c"
                },
                {
                    "_id": "674f57ec67b1cd441804b171",
                    "_tpl": "59d650cf86f7741b846413a4",
                    "slotId": "mod_sight_rear",
                    "upd": {
                        "Sight": {
                            "ScopesCurrentCalibPointIndexes": [
                                0
                            ],
                            "ScopesSelectedModes": [
                                0
                            ],
                            "SelectedScope": 0,
                            "ScopeZoomValue": 0
                        }
                    },
                    "parentId": "674f57ec67b1cd441804b16c"
                },
                {
                    "_id": "674f57ec67b1cd441804b172",
                    "_tpl": "59d6514b86f774171a068a08",
                    "slotId": "mod_stock",
                    "parentId": "674f57ec67b1cd441804b16c"
                },
                {
                    "_id": "674f57ec67b1cd441804b173",
                    "_tpl": "5a01c29586f77474660c694c",
                    "slotId": "mod_magazine",
                    "parentId": "674f57ec67b1cd441804b16c"
                },
                {
                    "_id": "674f57ec67b1cd441804b174",
                    "_tpl": "59d64f2f86f77417193ef8b3",
                    "slotId": "mod_handguard",
                    "parentId": "674f57ec67b1cd441804b16d"
                }
            ],
            "target": "674f57ec67b1cd441804b16c",
            "type": "Item",
            "unknown": false,
            "value": 1
        }
    ],
    "639873003693c63d86328f25": [
        {
            "findInRaid": true,
            "id": "674f5397b1f465c9d4b650c3",
            "index": 0,
            "items": [
                {
                    "_id": "674f580467b1cd441804b182",
                    "_tpl": "5c46fbd72e2216398b5a8c9c",
                    "upd": {
                        "Repairable": {
                            "MaxDurability": 100,
                            "Durability": 100
                        },
                        "Foldable": {
                            "Folded": false
                        },
                        "FireMode": {
                            "FireMode": "single"
                        }
                    }
                },
                {
                    "_id": "674f580467b1cd441804b183",
                    "_tpl": "5c471be12e221602b66cd9ac",
                    "slotId": "mod_pistol_grip",
                    "parentId": "674f580467b1cd441804b182"
                },
                {
                    "_id": "674f580467b1cd441804b184",
                    "_tpl": "5c471c442e221602b542a6f8",
                    "slotId": "mod_magazine",
                    "parentId": "674f580467b1cd441804b182"
                },
                {
                    "_id": "674f580467b1cd441804b185",
                    "_tpl": "5c471b5d2e221602b21d4e14",
                    "slotId": "mod_stock",
                    "parentId": "674f580467b1cd441804b182"
                },
                {
                    "_id": "674f580467b1cd441804b186",
                    "_tpl": "5c471cb32e221602b177afaa",
                    "slotId": "mod_barrel",
                    "parentId": "674f580467b1cd441804b182"
                },
                {
                    "_id": "674f580467b1cd441804b187",
                    "_tpl": "5c471c2d2e22164bef5d077f",
                    "slotId": "mod_mount_001",
                    "parentId": "674f580467b1cd441804b182"
                },
                {
                    "_id": "674f580467b1cd441804b188",
                    "_tpl": "5c471bd12e221602b4129c3a",
                    "slotId": "mod_reciever",
                    "parentId": "674f580467b1cd441804b182"
                },
                {
                    "_id": "674f580467b1cd441804b189",
                    "_tpl": "5c471bfc2e221602b21d4e17",
                    "slotId": "mod_muzzle",
                    "parentId": "674f580467b1cd441804b186"
                },
                {
                    "_id": "674f580467b1cd441804b18a",
                    "_tpl": "5c471c842e221615214259b5",
                    "slotId": "mod_gas_block",
                    "parentId": "674f580467b1cd441804b186"
                },
                {
                    "_id": "674f580467b1cd441804b18b",
                    "_tpl": "5c471c6c2e221602b66cd9ae",
                    "slotId": "mod_handguard",
                    "parentId": "674f580467b1cd441804b187"
                },
                {
                    "_id": "674f580467b1cd441804b18c",
                    "_tpl": "5c471b7e2e2216152006e46c",
                    "slotId": "mod_sight_rear",
                    "upd": {
                        "Sight": {
                            "ScopesCurrentCalibPointIndexes": [
                                0
                            ],
                            "ScopesSelectedModes": [
                                0
                            ],
                            "SelectedScope": 0,
                            "ScopeZoomValue": 0
                        }
                    },
                    "parentId": "674f580467b1cd441804b187"
                },
                {
                    "_id": "674f580467b1cd441804b18d",
                    "_tpl": "5c471ba12e221602b3137d76",
                    "slotId": "mod_sight_front",
                    "upd": {
                        "Sight": {
                            "ScopesCurrentCalibPointIndexes": [
                                0
                            ],
                            "ScopesSelectedModes": [
                                0
                            ],
                            "SelectedScope": 0,
                            "ScopeZoomValue": 0
                        }
                    },
                    "parentId": "674f580467b1cd441804b189"
                }
            ],
            "target": "674f580467b1cd441804b182",
            "type": "Item",
            "unknown": false,
            "value": 1
        }
    ],
    "5b477f7686f7744d1b23c4d2": [
        {
            "findInRaid": true,
            "id": "674f539bfcab30c62a899427",
            "index": 0,
            "items": [
                {
                    "_id": "674f582067b1cd441804c0ef",
                    "_tpl": "5aafa857e5b5b00018480968",
                    "upd": {
                        "Repairable": {
                            "MaxDurability": 100,
                            "Durability": 100
                        },
                        "FireMode": {
                            "FireMode": "single"
                        }
                    }
                },
                {
                    "_id": "674f582067b1cd441804c0f0",
                    "_tpl": "64b9e2037fdfb81df81e3c25",
                    "slotId": "mod_magazine",
                    "parentId": "674f582067b1cd441804c0ef"
                },
                {
                    "_id": "674f582067b1cd441804c0f1",
                    "_tpl": "5aaf8e43e5b5b00015693246",
                    "slotId": "mod_stock",
                    "parentId": "674f582067b1cd441804c0ef"
                },
                {
                    "_id": "674f582067b1cd441804c0f2",
                    "_tpl": "5aaf9d53e5b5b00015042a52",
                    "slotId": "mod_barrel",
                    "parentId": "674f582067b1cd441804c0ef"
                },
                {
                    "_id": "674f582067b1cd441804c0f3",
                    "_tpl": "5abcbb20d8ce87001773e258",
                    "slotId": "mod_sight_rear",
                    "upd": {
                        "Sight": {
                            "ScopesCurrentCalibPointIndexes": [
                                0
                            ],
                            "ScopesSelectedModes": [
                                0
                            ],
                            "SelectedScope": 0,
                            "ScopeZoomValue": 0
                        }
                    },
                    "parentId": "674f582067b1cd441804c0ef"
                },
                {
                    "_id": "674f582067b1cd441804c0f4",
                    "_tpl": "5ab24ef9e5b5b00fe93c9209",
                    "slotId": "mod_mount",
                    "parentId": "674f582067b1cd441804c0f1"
                },
                {
                    "_id": "674f582067b1cd441804c0f5",
                    "_tpl": "5aafa1c2e5b5b00015042a56",
                    "slotId": "mod_muzzle",
                    "parentId": "674f582067b1cd441804c0f2"
                },
                {
                    "_id": "674f582067b1cd441804c0f6",
                    "_tpl": "5aafa49ae5b5b00015042a58",
                    "slotId": "mod_sight_front",
                    "upd": {
                        "Sight": {
                            "ScopesCurrentCalibPointIndexes": [
                                0
                            ],
                            "ScopesSelectedModes": [
                                0
                            ],
                            "SelectedScope": 0,
                            "ScopeZoomValue": 0
                        }
                    },
                    "parentId": "674f582067b1cd441804c0f5"
                }
            ],
            "target": "674f582067b1cd441804c0ef",
            "type": "Item",
            "unknown": false,
            "value": 1
        }
    ],
    "63987301e11ec11ff5504036": [
        {
            "findInRaid": true,
            "id": "674f539e509d1abb910daf93",
            "index": 0,
            "items": [
                {
                    "_id": "674f584e67b1cd441804cec9",
                    "_tpl": "5bfea6e90db834001b7347f3",
                    "upd": {
                        "Repairable": {
                            "MaxDurability": 100,
                            "Durability": 100
                        },
                        "FireMode": {
                            "FireMode": "single"
                        }
                    }
                },
                {
                    "_id": "674f584e67b1cd441804ceca",
                    "_tpl": "5bfea7ad0db834001c38f1ee",
                    "slotId": "mod_magazine",
                    "parentId": "674f584e67b1cd441804cec9"
                },
                {
                    "_id": "674f584e67b1cd441804cecb",
                    "_tpl": "5bfeb32b0db834001a6694d9",
                    "slotId": "mod_stock",
                    "parentId": "674f584e67b1cd441804cec9"
                },
                {
                    "_id": "674f584e67b1cd441804cecc",
                    "_tpl": "5bfebc320db8340019668d79",
                    "slotId": "mod_barrel",
                    "parentId": "674f584e67b1cd441804cec9"
                },
                {
                    "_id": "674f584e67b1cd441804cecd",
                    "_tpl": "5d270b3c8abbc3105335cfb8",
                    "slotId": "mod_muzzle",
                    "parentId": "674f584e67b1cd441804cecc"
                }
            ],
            "target": "674f584e67b1cd441804cec9",
            "type": "Item",
            "unknown": false,
            "value": 1
        },
        {
            "findInRaid": true,
            "id": "674f53a92b8089ce5377a9cf",
            "index": 1,
            "items": [
                {
                    "_id": "674f585b67b1cd441804cece",
                    "_tpl": "5e81c3cbac2bb513793cdc75",
                    "upd": {
                        "Repairable": {
                            "MaxDurability": 100,
                            "Durability": 100
                        },
                        "FireMode": {
                            "FireMode": "single"
                        }
                    }
                },
                {
                    "_id": "674f585b67b1cd441804cecf",
                    "_tpl": "5e81c519cb2b95385c177551",
                    "slotId": "mod_barrel",
                    "parentId": "674f585b67b1cd441804cece"
                },
                {
                    "_id": "674f585b67b1cd441804ced0",
                    "_tpl": "5e81c6bf763d9f754677beff",
                    "slotId": "mod_pistol_grip",
                    "parentId": "674f585b67b1cd441804cece"
                },
                {
                    "_id": "674f585b67b1cd441804ced1",
                    "_tpl": "5e81edc13397a21db957f6a1",
                    "slotId": "mod_reciever",
                    "parentId": "674f585b67b1cd441804cece"
                },
                {
                    "_id": "674f585b67b1cd441804ced2",
                    "_tpl": "5e81c4ca763d9f754677befa",
                    "slotId": "mod_magazine",
                    "parentId": "674f585b67b1cd441804cece"
                },
                {
                    "_id": "674f585b67b1cd441804ced3",
                    "_tpl": "5e81c6a2ac2bb513793cdc7f",
                    "slotId": "mod_trigger",
                    "parentId": "674f585b67b1cd441804cece"
                },
                {
                    "_id": "674f585b67b1cd441804ced4",
                    "_tpl": "5e81c550763d9f754677befd",
                    "slotId": "mod_hammer",
                    "parentId": "674f585b67b1cd441804cece"
                },
                {
                    "_id": "674f585b67b1cd441804ced5",
                    "_tpl": "5e81c539cb2b95385c177553",
                    "slotId": "mod_catch",
                    "parentId": "674f585b67b1cd441804cece"
                },
                {
                    "_id": "674f585b67b1cd441804ced6",
                    "_tpl": "5e81ee4dcb2b95385c177582",
                    "slotId": "mod_sight_rear",
                    "upd": {
                        "Sight": {
                            "ScopesCurrentCalibPointIndexes": [
                                0
                            ],
                            "ScopesSelectedModes": [
                                0
                            ],
                            "SelectedScope": 0,
                            "ScopeZoomValue": 0
                        }
                    },
                    "parentId": "674f585b67b1cd441804ced1"
                },
                {
                    "_id": "674f585b67b1cd441804ced7",
                    "_tpl": "5e81ee213397a21db957f6a6",
                    "slotId": "mod_sight_front",
                    "upd": {
                        "Sight": {
                            "ScopesCurrentCalibPointIndexes": [
                                0
                            ],
                            "ScopesSelectedModes": [
                                0
                            ],
                            "SelectedScope": 0,
                            "ScopeZoomValue": 0
                        }
                    },
                    "parentId": "674f585b67b1cd441804ced1"
                }
            ],
            "target": "674f585b67b1cd441804cece",
            "type": "Item",
            "unknown": false,
            "value": 1
        }
    ],
    "5b47825886f77468074618d3": [
        {
            "findInRaid": true,
				"id": "674f53aba3070b0ec8b33c9f",
				"index": 0,
				"items": [
					{
						"_id": "674f587667b1cd441804ced8",
						"_tpl": "5447a9cd4bdc2dbd208b4567",
						"upd": {
							"Repairable": {
								"MaxDurability": 100,
								"Durability": 100
							},
							"FireMode": {
								"FireMode": "single"
							}
						}
					},
					{
						"_id": "674f587667b1cd441804ced9",
						"_tpl": "55d4b9964bdc2d1d4e8b456e",
						"slotId": "mod_pistol_grip",
						"parentId": "674f587667b1cd441804ced8"
					},
					{
						"_id": "674f587667b1cd441804ceda",
						"_tpl": "55d4887d4bdc2d962f8b4570",
						"slotId": "mod_magazine",
						"parentId": "674f587667b1cd441804ced8"
					},
					{
						"_id": "674f587667b1cd441804cedb",
						"_tpl": "55d355e64bdc2d962f8b4569",
						"slotId": "mod_reciever",
						"parentId": "674f587667b1cd441804ced8"
					},
					{
						"_id": "674f587667b1cd441804cedc",
						"_tpl": "5649be884bdc2d79388b4577",
						"slotId": "mod_stock",
						"parentId": "674f587667b1cd441804ced8"
					},
					{
						"_id": "674f587667b1cd441804cedd",
						"_tpl": "55d44fd14bdc2d962f8b456e",
						"slotId": "mod_charge",
						"parentId": "674f587667b1cd441804ced8"
					},
					{
						"_id": "674f587667b1cd441804cede",
						"_tpl": "55d3632e4bdc2d972f8b4569",
						"slotId": "mod_barrel",
						"parentId": "674f587667b1cd441804cedb"
					},
					{
						"_id": "674f587667b1cd441804cedf",
						"_tpl": "5ae30db85acfc408fb139a05",
						"slotId": "mod_handguard",
						"parentId": "674f587667b1cd441804cedb"
					},
					{
						"_id": "674f587667b1cd441804cee0",
						"_tpl": "5ae30bad5acfc400185c2dc4",
						"slotId": "mod_sight_rear",
						"upd": {
							"Sight": {
								"ScopesCurrentCalibPointIndexes": [
									0
								],
								"ScopesSelectedModes": [
									0
								],
								"SelectedScope": 0,
								"ScopeZoomValue": 0
							}
						},
						"parentId": "674f587667b1cd441804cedb"
					},
					{
						"_id": "674f587667b1cd441804cee1",
						"_tpl": "55d4ae6c4bdc2d8b2f8b456e",
						"slotId": "mod_stock_000",
						"parentId": "674f587667b1cd441804cedc"
					},
					{
						"_id": "674f587667b1cd441804cee2",
						"_tpl": "544a38634bdc2d58388b4568",
						"slotId": "mod_muzzle",
						"parentId": "674f587667b1cd441804cede"
					},
					{
						"_id": "674f587667b1cd441804cee3",
						"_tpl": "5ae30e795acfc408fb139a0b",
						"slotId": "mod_gas_block",
						"parentId": "674f587667b1cd441804cede"
					},
					{
						"_id": "674f587667b1cd441804cee4",
						"_tpl": "637f57a68d137b27f70c4968",
						"slotId": "mod_handguard",
						"parentId": "674f587667b1cd441804cedf"
					}
				],
				"target": "674f587667b1cd441804ced8",
				"type": "Item",
				"unknown": false,
				"value": 1
        }
    ],
    "64f83bb69878a0569d6ecfbe" : [
        {
            "findInRaid": true,
				"id": "674f53ae5fb0e1be2c50b2b1",
				"index": 0,
				"items": [
					{
						"_id": "674f588b67b1cd441804df11",
						"_tpl": "606587252535c57a13424cfd",
						"upd": {
							"Repairable": {
								"MaxDurability": 100,
								"Durability": 100
							},
							"FireMode": {
								"FireMode": "single"
							}
						}
					},
					{
						"_id": "674f588b67b1cd441804df12",
						"_tpl": "55802f5d4bdc2dac148b458f",
						"slotId": "mod_pistol_grip",
						"parentId": "674f588b67b1cd441804df11"
					},
					{
						"_id": "674f588b67b1cd441804df13",
						"_tpl": "59d6272486f77466146386ff",
						"slotId": "mod_magazine",
						"parentId": "674f588b67b1cd441804df11"
					},
					{
						"_id": "674f588b67b1cd441804df14",
						"_tpl": "606587a88900dc2d9a55b659",
						"slotId": "mod_reciever",
						"parentId": "674f588b67b1cd441804df11"
					},
					{
						"_id": "674f588b67b1cd441804df15",
						"_tpl": "606587e18900dc2d9a55b65f",
						"slotId": "mod_stock_001",
						"parentId": "674f588b67b1cd441804df11"
					},
					{
						"_id": "674f588b67b1cd441804df16",
						"_tpl": "606587bd6d0bd7580617bacc",
						"slotId": "mod_charge",
						"parentId": "674f588b67b1cd441804df11"
					},
					{
						"_id": "674f588b67b1cd441804df17",
						"_tpl": "60658776f2cb2e02a42ace2b",
						"slotId": "mod_barrel",
						"parentId": "674f588b67b1cd441804df14"
					},
					{
						"_id": "674f588b67b1cd441804df18",
						"_tpl": "6065880c132d4d12c81fd8da",
						"slotId": "mod_handguard",
						"parentId": "674f588b67b1cd441804df14"
					},
					{
						"_id": "674f588b67b1cd441804df19",
						"_tpl": "5bc09a18d4351e003562b68e",
						"slotId": "mod_sight_rear",
						"upd": {
							"Sight": {
								"ScopesCurrentCalibPointIndexes": [
									0
								],
								"ScopesSelectedModes": [
									0
								],
								"SelectedScope": 0,
								"ScopeZoomValue": 0
							}
						},
						"parentId": "674f588b67b1cd441804df14"
					},
					{
						"_id": "674f588b67b1cd441804df1a",
						"_tpl": "606587d11246154cad35d635",
						"slotId": "mod_stock_000",
						"parentId": "674f588b67b1cd441804df15"
					},
					{
						"_id": "674f588b67b1cd441804df1b",
						"_tpl": "6065c6e7132d4d12c81fd8e1",
						"slotId": "mod_muzzle",
						"parentId": "674f588b67b1cd441804df17"
					},
					{
						"_id": "674f588b67b1cd441804df1c",
						"_tpl": "6065dc8a132d4d12c81fd8e3",
						"slotId": "mod_gas_block",
						"parentId": "674f588b67b1cd441804df17"
					},
					{
						"_id": "674f588b67b1cd441804df1d",
						"_tpl": "5bc09a30d4351e00367fb7c8",
						"slotId": "mod_sight_front",
						"upd": {
							"Sight": {
								"ScopesCurrentCalibPointIndexes": [
									0
								],
								"ScopesSelectedModes": [
									0
								],
								"SelectedScope": 0,
								"ScopeZoomValue": 0
							}
						},
						"parentId": "674f588b67b1cd441804df18"
					}
				],
				"target": "674f588b67b1cd441804df11",
				"type": "Item",
				"unknown": false,
				"value": 1
        }
    ],
    "64f83bcdde58fc437700d8fa" : [
        {
            "findInRaid": true,
				"id": "674f53b1da81d1ef9d30c9e8",
				"index": 0,
				"items": [
					{
						"_id": "674f58a567b1cd441804df2c",
						"_tpl": "5df8ce05b11454561e39243b",
						"upd": {
							"Repairable": {
								"MaxDurability": 100,
								"Durability": 100
							},
							"FireMode": {
								"FireMode": "single"
							}
						}
					},
					{
						"_id": "674f58a567b1cd441804df2d",
						"_tpl": "55d4b9964bdc2d1d4e8b456e",
						"slotId": "mod_pistol_grip",
						"parentId": "674f58a567b1cd441804df2c"
					},
					{
						"_id": "674f58a567b1cd441804df2e",
						"_tpl": "5df8f541c41b2312ea3335e3",
						"slotId": "mod_magazine",
						"parentId": "674f58a567b1cd441804df2c"
					},
					{
						"_id": "674f58a567b1cd441804df2f",
						"_tpl": "5649be884bdc2d79388b4577",
						"slotId": "mod_stock",
						"parentId": "674f58a567b1cd441804df2c"
					},
					{
						"_id": "674f58a567b1cd441804df30",
						"_tpl": "5df8e4080b92095fd441e594",
						"slotId": "mod_reciever",
						"parentId": "674f58a567b1cd441804df2c"
					},
					{
						"_id": "674f58a567b1cd441804df31",
						"_tpl": "5df8e053bb49d91fb446d6a6",
						"slotId": "mod_charge",
						"parentId": "674f58a567b1cd441804df2c"
					},
					{
						"_id": "674f58a567b1cd441804df32",
						"_tpl": "5ae30c9a5acfc408fb139a03",
						"slotId": "mod_stock_000",
						"parentId": "674f58a567b1cd441804df2f"
					},
					{
						"_id": "674f58a567b1cd441804df33",
						"_tpl": "5df917564a9f347bc92edca3",
						"slotId": "mod_barrel",
						"parentId": "674f58a567b1cd441804df30"
					},
					{
						"_id": "674f58a567b1cd441804df34",
						"_tpl": "5df916dfbb49d91fb446d6b9",
						"slotId": "mod_handguard",
						"parentId": "674f58a567b1cd441804df30"
					},
					{
						"_id": "674f58a567b1cd441804df35",
						"_tpl": "5dfa3d7ac41b2312ea33362a",
						"slotId": "mod_sight_rear",
						"upd": {
							"Sight": {
								"ScopesCurrentCalibPointIndexes": [
									0
								],
								"ScopesSelectedModes": [
									0
								],
								"SelectedScope": 0,
								"ScopeZoomValue": 0
							}
						},
						"parentId": "674f58a567b1cd441804df30"
					},
					{
						"_id": "674f58a567b1cd441804df36",
						"_tpl": "5dfa3cd1b33c0951220c079b",
						"slotId": "mod_muzzle",
						"parentId": "674f58a567b1cd441804df33"
					},
					{
						"_id": "674f58a567b1cd441804df37",
						"_tpl": "5dfa3d45dfc58d14537c20b0",
						"slotId": "mod_gas_block",
						"parentId": "674f58a567b1cd441804df33"
					},
					{
						"_id": "674f58a567b1cd441804df38",
						"_tpl": "5dfa3d950dee1b22f862eae0",
						"slotId": "mod_sight_front",
						"upd": {
							"Sight": {
								"ScopesCurrentCalibPointIndexes": [
									0
								],
								"ScopesSelectedModes": [
									0
								],
								"SelectedScope": 0,
								"ScopeZoomValue": 0
							}
						},
						"parentId": "674f58a567b1cd441804df34"
					}
				],
				"target": "674f58a567b1cd441804df2c",
				"type": "Item",
				"unknown": false,
				"value": 1
        }
    ]
}